pantsbuild.pants.contrib.thrifty-1.28.0-py3.6-nspkg.pth
pants/contrib/thrifty/__init__.py
pants/contrib/thrifty/java_thrifty_gen.py
pants/contrib/thrifty/java_thrifty_library.py
pants/contrib/thrifty/register.py
pants/contrib/thrifty/target_types.py
pantsbuild.pants.contrib.thrifty-1.28.0.dist-info/METADATA
pantsbuild.pants.contrib.thrifty-1.28.0.dist-info/WHEEL
pantsbuild.pants.contrib.thrifty-1.28.0.dist-info/entry_points.txt
pantsbuild.pants.contrib.thrifty-1.28.0.dist-info/namespace_packages.txt
pantsbuild.pants.contrib.thrifty-1.28.0.dist-info/top_level.txt
pantsbuild.pants.contrib.thrifty-1.28.0.dist-info/zip-safe
pantsbuild.pants.contrib.thrifty-1.28.0.dist-info/RECORD
